ua_stache_api/__init__.py
ua_stache_api/tests/test_get.json
ua_stache_api/tests/test_post.json
ua_stache_api/tests/test_ua_stache_api.py
ua_stache_api/ua_stache_api.py
ua_stache_api-2.1.1.dist-info/LICENSE
ua_stache_api-2.1.1.dist-info/METADATA
ua_stache_api-2.1.1.dist-info/WHEEL
ua_stache_api-2.1.1.dist-info/RECORD
