Metadata-Version: 2.1
Name: ua-stache-api
Version: 2.1.1
Summary: Allows the caller to easily get "secret" information from stache entries at [https://stache.arizona.edu].
Author: Your Name
Author-email: you@example.com
Requires-Python: >=3.11,<4.0
Classifier: Programming Language :: Python :: 3
Classifier: Programming Language :: Python :: 3.11
Classifier: Programming Language :: Python :: 3.12
Requires-Dist: requests (>=2.31.0,<3.0.0)
